wp_utils/__init__.py
wp_utils/settings.py
wp_utils/application/__init__.py
wp_utils/application/admin.py
wp_utils/application/version.py
wp_utils/logging/__init__.py
wp_utils/logging/backoff.py
wp_utils/logging/formatters.py
wp_utils/logging/loggers.py
wp_utils/logging/mixins.py
wp_utils/logging/solr.py
wp_utils/tools/__init__.py
wp_utils/tools/generation.py
webportal_utils-0.2.11.dist-info/METADATA
webportal_utils-0.2.11.dist-info/WHEEL
webportal_utils-0.2.11.dist-info/licenses/LICENCE
webportal_utils-0.2.11.dist-info/RECORD
