Metadata-Version: 2.3
Name: webportal-utils
Version: 0.2.11
Summary: Пакет утилит для webportal.
Author-email: Nikita Sysoev <nylinary@gmail.com>
License-File: LICENCE
Classifier: License :: OSI Approved :: MIT License
Classifier: Operating System :: OS Independent
Classifier: Programming Language :: Python :: 3
Requires-Python: >=3.9
Requires-Dist: django-environ~=0.9.0
Requires-Dist: django>=3.2.15
Requires-Dist: pysolr~=3.9.0
Requires-Dist: python-json-logger~=2.0.7
